__init__.py
biomechzoo/__init__.py
biomechzoo/__main__.py
biomechzoo/biomechzoo.py
biomechzoo/biomech_ops/__init__.py
biomechzoo/biomech_ops/continuous_relative_phase_data.py
biomechzoo/biomech_ops/continuous_relative_phase_line.py
biomechzoo/biomech_ops/filter_data.py
biomechzoo/biomech_ops/filter_line.py
biomechzoo/biomech_ops/movement_onset.py
biomechzoo/biomech_ops/normalize_data.py
biomechzoo/biomech_ops/normalize_line.py
biomechzoo/biomech_ops/phase_angle_data.py
biomechzoo/biomech_ops/phase_angle_line.py
biomechzoo/conversion/__init__.py
biomechzoo/conversion/c3d2zoo_data.py
biomechzoo/conversion/mvnx2zoo_data.py
biomechzoo/conversion/opencap2zoo_data.py
biomechzoo/conversion/table2zoo_data.py
biomechzoo/imu/__init__.py
biomechzoo/imu/kinematics.py
biomechzoo/imu/step_detection.py
biomechzoo/imu/tilt_algorithm.py
biomechzoo/linear_algebra_ops/__init__.py
biomechzoo/linear_algebra_ops/compute_magnitude_data.py
biomechzoo/linear_algebra_ops/rectify.py
biomechzoo/mvn/__init__.py
biomechzoo/mvn/load_mvnx.py
biomechzoo/mvn/main_mvnx.py
biomechzoo/mvn/mvn.py
biomechzoo/mvn/mvnx_file_accessor.py
biomechzoo/processing/__init__.py
biomechzoo/processing/addchannel_data.py
biomechzoo/processing/addevent_data.py
biomechzoo/processing/explodechannel_data.py
biomechzoo/processing/partition_data.py
biomechzoo/processing/removechannel_data.py
biomechzoo/processing/removeevent_data.py
biomechzoo/processing/renamechannel_data.py
biomechzoo/processing/renameevent_data.py
biomechzoo/processing/rep_trial_data.py
biomechzoo/processing/split_trial_data.py
biomechzoo/statistics/__init__.py
biomechzoo/statistics/eventval.py
biomechzoo/statistics/rmse.py
biomechzoo/utils/__init__.py
biomechzoo/utils/batchdisp.py
biomechzoo/utils/combine_xsens_csv.py
biomechzoo/utils/common_substring.py
biomechzoo/utils/compute_sampling_rate_from_time.py
biomechzoo/utils/engine.py
biomechzoo/utils/findfield.py
biomechzoo/utils/get_split_events.py
biomechzoo/utils/group_by_terminal_folder.py
biomechzoo-0.7.4.dist-info/licenses/LICENSE
biomechzoo-0.7.4.dist-info/METADATA
biomechzoo-0.7.4.dist-info/WHEEL
biomechzoo-0.7.4.dist-info/entry_points.txt
biomechzoo-0.7.4.dist-info/top_level.txt
biomechzoo-0.7.4.dist-info/RECORD
