Metadata-Version: 2.4
Name: biomechzoo
Version: 0.7.4
Summary: Python implementation of the biomechZoo toolbox
License-Expression: MIT
Project-URL: Homepage, https://github.com/mcgillmotionlab/biomechzoo
Requires-Python: <3.12,>=3.11
License-File: LICENSE
Requires-Dist: ezc3d>=1.5.19
Requires-Dist: matplotlib>=3.10.6
Requires-Dist: numpy==2.2.6
Requires-Dist: pandas>=2.3.2
Requires-Dist: scipy>=1.16.2
Requires-Dist: pyarrow>=19.0.0
Requires-Dist: plotly>=6.4.0
Requires-Dist: kaleido>=1.2.0
Requires-Dist: dash>=3.3.0
Dynamic: license-file
